[
  {
    "verse": 1,
    "type": "superscription_thanksgiving_tetragrammaton",
    "tier_status": "Layer 2 (superscription + per-chapter first-occurrence footnote) — divine_names_table_2026-05",
    "explanation_thai": "‘บทเพลงสดุดีสำหรับการขอบพระคุณ’ (מִזְמוֹר לְתוֹדָה) — คำนำที่นับรวมในข้อ 1 (เลขข้อตรงกับฉบับอังกฤษ/BSB). תּוֹדָה หมายถึงเครื่องบูชาแห่งการขอบพระคุณ. **องค์พระผู้เป็นเจ้า** (ปรากฏครั้งแรกที่ข้อ 1) แปลจาก יהוה (พระนามเฉพาะของพระเจ้า ออกเสียงว่า ‘ยาห์เวห์’) ฉบับเอเรโมสใช้ตามแบบแผนของฉบับพันธสัญญาใหม่ที่แปล κύριος. บทสั้นๆ บทนี้เป็นคำเชิญชวนให้ทั้งโลกมานมัสการพระเจ้าด้วยความยินดี. ดูรายละเอียดที่ docs/translator_decisions/divine_names_table_2026-05.md."
  },
  {
    "verse": 3,
    "type": "we_are_his_sheep",
    "tier_status": "Layer 2 (exegetical footnote)",
    "explanation_thai": "‘พระองค์ทรงสร้างเรา และเราเป็นของพระองค์ เราเป็นประชากรของพระองค์ และเป็นฝูงแกะแห่งทุ่งหญ้าของพระองค์’ — ภาพความสัมพันธ์แห่งพันธสัญญา พระเจ้าทรงเป็นผู้เลี้ยงและเราเป็นฝูงแกะของพระองค์ (เทียบ สดด 95:7; 23) ภาพนี้สำเร็จในพระเยซู ‘ผู้เลี้ยงที่ดี’ (ยน 10:11, 14)."
  }
]